AUTHORS.txt
CHANGELOG.txt
LICENSE.txt
README.txt
setup.py
coopr/__init__.py
coopr.data.pyomo.egg-info/PKG-INFO
coopr.data.pyomo.egg-info/SOURCES.txt
coopr.data.pyomo.egg-info/dependency_links.txt
coopr.data.pyomo.egg-info/namespace_packages.txt
coopr.data.pyomo.egg-info/top_level.txt
coopr/data/__init__.py
coopr/data/pyomo/TODOs
coopr/data/pyomo/__init__.py
coopr/data/pyomo/diet1.dat
coopr/data/pyomo/diet1.json
coopr/data/pyomo/diet1.py
coopr/data/pyomo/diet1.yml
coopr/data/pyomo/solvers.py
coopr/data/pyomo/test_baselines.json
coopr/data/pyomo/test_baselines.py
coopr/data/pyomo/test_baselines.yml
coopr/data/pyomo/test_perf.py
coopr/data/pyomo/test_solvers.yml
coopr/data/pyomo/performance/set1-100.dat
coopr/data/pyomo/performance/set1-1000.dat
coopr/data/pyomo/performance/set1-10000.dat
coopr/data/pyomo/performance/set1.py
coopr/data/pyomo/plugins/__init__.py
coopr/data/pyomo/plugins/lp.py
coopr/data/pyomo/plugins/mip.py
coopr/data/pyomo/problems/constant1a.py
coopr/data/pyomo/problems/constant1a.yml
coopr/data/pyomo/problems/constant1b.py
coopr/data/pyomo/problems/constant1b.yml
coopr/data/pyomo/problems/diet1.dat
coopr/data/pyomo/problems/diet1.py
coopr/data/pyomo/problems/diet1.yml
coopr/data/pyomo/problems/infeasible1a.py
coopr/data/pyomo/problems/infeasible1b.py
coopr/data/pyomo/problems/lp_basic.py
coopr/data/pyomo/problems/lp_basic.yml
coopr/data/pyomo/problems/lp_unique1.py
coopr/data/pyomo/problems/lp_unique1.yml
coopr/data/pyomo/problems/lp_unique1_proof.py
coopr/data/pyomo/problems/mip_constant1a.py
coopr/data/pyomo/problems/mip_constant1a.yml
coopr/data/pyomo/problems/mip_infeasible1a.py
coopr/data/pyomo/problems/mip_infeasible1a.yml
coopr/data/pyomo/problems/mip_unbounded1a.py
coopr/data/pyomo/problems/mip_unique1.py
coopr/data/pyomo/problems/mip_unique1.yml
coopr/data/pyomo/problems/multidimen_sos1.py
coopr/data/pyomo/problems/multidimen_sos1.yml
coopr/data/pyomo/problems/multidimen_sos2.py
coopr/data/pyomo/problems/multidimen_sos2.yml
coopr/data/pyomo/problems/simple1a.py
coopr/data/pyomo/problems/simple1a.yml
coopr/data/pyomo/problems/simple1b.py
coopr/data/pyomo/problems/simple1b.yml
coopr/data/pyomo/problems/sos1.py
coopr/data/pyomo/problems/sos1.yml
