Metadata-Version: 1.0
Name: coopr.data.pyomo
Version: 1.2.1
Summary: Coopr data project:  Pyomo test models
Home-page: https://software.sandia.gov/svn/public/coopr/coopr.data.pyomo
Author: William E. Hart
Author-email: wehart@sandia.gov
License: BSD
Keywords: optimization
Platform: any
Classifier: Development Status :: 2 - Pre-Alpha
Classifier: Intended Audience :: End Users/Desktop
Classifier: Intended Audience :: Science/Research
Classifier: License :: OSI Approved :: BSD License
Classifier: Natural Language :: English
Classifier: Operating System :: Microsoft :: Windows
Classifier: Operating System :: Unix
Classifier: Programming Language :: Python
Classifier: Programming Language :: Unix Shell
Classifier: Topic :: Scientific/Engineering :: Mathematics
Classifier: Topic :: Software Development :: Libraries :: Python Modules
Classifier: Topic :: Scientific/Engineering
